LICENSE
NOTICE
README.md
requirements.txt
setup.py
cytomine/__init__.py
cytomine/cytomine.py
cytomine/models/__init__.py
cytomine/models/annotation.py
cytomine/models/collection.py
cytomine/models/image.py
cytomine/models/imagegroup.py
cytomine/models/model.py
cytomine/models/ontology.py
cytomine/models/project.py
cytomine/models/property.py
cytomine/models/social.py
cytomine/models/storage.py
cytomine/models/track.py
cytomine/models/user.py
cytomine/models/_utilities/__init__.py
cytomine/models/_utilities/dump.py
cytomine/models/_utilities/parallel.py
cytomine/models/_utilities/pattern_matching.py
cytomine/utilities/__init__.py
cytomine/utilities/annotations.py
cytomine_python_client.egg-info/PKG-INFO
cytomine_python_client.egg-info/SOURCES.txt
cytomine_python_client.egg-info/dependency_links.txt
cytomine_python_client.egg-info/requires.txt
cytomine_python_client.egg-info/top_level.txt
tests/test_annotation.py
tests/test_image.py
tests/test_ontology.py
tests/test_pattern_matching.py
tests/test_project.py
tests/test_property.py
tests/test_social.py
tests/test_storage.py
tests/test_user.py