Metadata-Version: 2.4
Name: cytomine-python-client
Version: 3.1.0
Summary: Python client to interact with Cytomine.
Home-page: https://uliege.cytomine.org
License: LICENSE
Classifier: License :: OSI Approved :: Apache Software License
Classifier: Programming Language :: Python :: 3.5
Classifier: Programming Language :: Python :: 3.6
Classifier: Programming Language :: Python :: 3.7
Classifier: Programming Language :: Python :: 3.8
Classifier: Operating System :: OS Independent
License-File: LICENSE
License-File: NOTICE
Requires-Dist: requests-toolbelt>=0.8.0
Requires-Dist: CacheControl>=0.12.10
Requires-Dist: Shapely>=1.6.4
Requires-Dist: six>=1.11.0
Requires-Dist: requests>=2.27.1
Requires-Dist: urllib3>=1.25.2
Dynamic: classifier
Dynamic: description
Dynamic: description-content-type
Dynamic: home-page
Dynamic: license
Dynamic: license-file
Dynamic: requires-dist
Dynamic: summary
